ImgToolBox/ImgFile.py
ImgToolBox/ImgToolBox.py
ImgToolBox/__init__.py
ImgToolBox-1.6.1.dist-info/LICENSE
ImgToolBox-1.6.1.dist-info/METADATA
ImgToolBox-1.6.1.dist-info/WHEEL
ImgToolBox-1.6.1.dist-info/top_level.txt
ImgToolBox-1.6.1.dist-info/RECORD
