Metadata-Version: 2.1
Name: ImgToolBox
Version: 1.6.1
Summary: A package about the transformations between raw, csv and numpy array
Home-page: https://github.com/LiaoU3/ImageToolBox.git
Author: LiaoU3
Author-email: vincent932693@gmail.com
Classifier: Programming Language :: Python :: 3
Classifier: License :: OSI Approved :: MIT License
Classifier: Operating System :: OS Independent
License-File: LICENSE
